fedml_databricks/__init__.py
fedml_databricks/databricks_cli_configure.sh
fedml_databricks/dbconnection.py
fedml_databricks/deployment_helper.py
fedml_databricks/kubectl_install_validate.sh
fedml_databricks/kyma_deploy.py
fedml_databricks/logger.py
fedml_databricks/predict.py
fedml_databricks/acr/__init__.py
fedml_databricks/acr/acr_kyma_deploy.py
fedml_databricks/acr/acr_kyma_deploy.sh
fedml_databricks/ecr/__init__.py
fedml_databricks/ecr/ecr_kyma_deploy.py
fedml_databricks/ecr/ecr_kyma_deploy.sh
fedml_databricks-1.0.5.data/scripts/acr_kyma_deploy.sh
fedml_databricks-1.0.5.data/scripts/databricks_cli_configure.sh
fedml_databricks-1.0.5.data/scripts/ecr_kyma_deploy.sh
fedml_databricks-1.0.5.data/scripts/kubectl_install_validate.sh
fedml_databricks-1.0.5.dist-info/LICENSE.txt
fedml_databricks-1.0.5.dist-info/METADATA
fedml_databricks-1.0.5.dist-info/WHEEL
fedml_databricks-1.0.5.dist-info/top_level.txt
fedml_databricks-1.0.5.dist-info/RECORD
