Metadata-Version: 2.1
Name: fedml_databricks
Version: 1.0.5
Summary: A python library for building machine learning models on Databricks using a federated data source
Author: SAP SE
License: Apache License 2.0
Classifier: Programming Language :: Python :: 3
Classifier: Operating System :: OS Independent
Requires-Python: >=3
License-File: LICENSE.txt
Requires-Dist: hdbcli
Requires-Dist: pandas
Requires-Dist: pyspark
Requires-Dist: ruamel.yaml
Requires-Dist: requests
Requires-Dist: mlflow
Requires-Dist: databricks-cli
